pipwin/__init__.py
pipwin/__main__.py
pipwin/command.py
pipwin/pipwin.py
pipwin-0.5.0.dist-info/METADATA
pipwin-0.5.0.dist-info/RECORD
pipwin-0.5.0.dist-info/WHEEL
pipwin-0.5.0.dist-info/entry_points.txt
pipwin-0.5.0.dist-info/top_level.txt
