Metadata-Version: 1.1
Name: pipwin
Version: 0.5.0
Summary: pipwin installs compiled python binaries on windows provided by Christoph Gohlke
Home-page: https://github.com/lepisma/pipwin
Author: lepisma
Author-email: abhinav.tushar.vs@gmail.com
License: BSD
Keywords: pipwin windows binaries
Platform: UNKNOWN
Classifier: Development Status :: 3 - Alpha
Classifier: Environment :: Console
Classifier: Operating System :: Microsoft :: Windows
Classifier: Programming Language :: Python :: 2
Classifier: Programming Language :: Python :: 3
